urnparse/__init__.py
urnparse/py.typed
urnparse/version.py
urnparse-0.2.2.dist-info/LICENSE
urnparse-0.2.2.dist-info/METADATA
urnparse-0.2.2.dist-info/WHEEL
urnparse-0.2.2.dist-info/top_level.txt
urnparse-0.2.2.dist-info/RECORD
