Metadata-Version: 2.1
Name: urnparse
Version: 0.2.2
Summary: Python library for generating and parsing and RFC 8141 compliant uniform resource names (URN).
Home-page: https://github.com/oarepo/urnparse
Author: Miroslav Bauer @ CESNET
Author-email: bauer@cesnet.cz
License: MIT
Platform: any
Classifier: Environment :: Web Environment
Classifier: Intended Audience :: Developers
Classifier: License :: OSI Approved :: MIT License
Classifier: Operating System :: OS Independent
Classifier: Programming Language :: Python
Classifier: Topic :: Internet :: WWW/HTTP :: Dynamic Content
Classifier: Topic :: Software Development :: Libraries :: Python Modules
Classifier: Programming Language :: Python :: 2
Classifier: Programming Language :: Python :: 2.7
Classifier: Programming Language :: Python :: 3
Classifier: Programming Language :: Python :: 3.5
Classifier: Development Status :: 4 - Beta
License-File: LICENSE
Requires-Dist: typing_extensions>=4.11.0
Provides-Extra: tests
Requires-Dist: pydocstyle; extra == "tests"
Requires-Dist: isort; extra == "tests"
Requires-Dist: check-manifest; extra == "tests"
Requires-Dist: pytest; extra == "tests"
